{
  "genres": {
    "withCounts": [
      "Animation (4326)",
      "Comedy (2663)",
      "Action (1946)",
      "Drama (1581)",
      "Adventure (1526)",
      "Fantasy (1098)",
      "Sci-Fi (1063)",
      "Sci-Fi & Fantasy (949)",
      "Romance (872)",
      "Action & Adventure (800)",
      "School (641)",
      "Slice of Life (554)",
      "Supernatural (520)",
      "Mecha (475)",
      "Kids (420)",
      "Mystery (416)",
      "Magic (410)",
      "Ecchi (373)",
      "Historical (314)",
      "Super Power (242)",
      "Music (233)",
      "Sports (222)",
      "Horror (204)",
      "Military (202)",
      "Space (184)",
      "Parody (183)",
      "Family (178)",
      "Harem (168)",
      "Martial Arts (153)",
      "Psychological (137)",
      "Demons (136)",
      "Crime (122)",
      "Game (113)",
      "Police (90)",
      "Friendship (88)",
      "Anime Influenced (74)",
      "Mahou Shoujo (67)",
      "Vampire (59)",
      "Samurai (59)",
      "Thriller (58)",
      "Shounen Ai (46)",
      "Shoujo Ai (41)",
      "Short (34)",
      "Cars (33)",
      "Sport (32)",
      "War & Politics (30)",
      "Dementia (28)",
      "Yaoi (20)",
      "Racing (18)",
      "Food (17)",
      "History (15)",
      "Zombies (13)",
      "Workplace (11)",
      "Gore (9)",
      "Gender Bender (8)",
      "Medical (8)",
      "Political (7)",
      "Yuri (7)",
      "Doujinshi (7)",
      "Documentary (5)",
      "Isekai (2)",
      "Tragedy (2)",
      "Soap (2)",
      "Mature (1)",
      "Law (1)",
      "Mahou Shounen (1)",
      "Adult (1)",
      "Cooking (1)",
      "Musical (1)",
      "Western (1)"
    ],
    "list": [
      {
        "name": "Animation",
        "count": 4326
      },
      {
        "name": "Comedy",
        "count": 2663
      },
      {
        "name": "Action",
        "count": 1946
      },
      {
        "name": "Drama",
        "count": 1581
      },
      {
        "name": "Adventure",
        "count": 1526
      },
      {
        "name": "Fantasy",
        "count": 1098
      },
      {
        "name": "Sci-Fi",
        "count": 1063
      },
      {
        "name": "Sci-Fi & Fantasy",
        "count": 949
      },
      {
        "name": "Romance",
        "count": 872
      },
      {
        "name": "Action & Adventure",
        "count": 800
      },
      {
        "name": "School",
        "count": 641
      },
      {
        "name": "Slice of Life",
        "count": 554
      },
      {
        "name": "Supernatural",
        "count": 520
      },
      {
        "name": "Mecha",
        "count": 475
      },
      {
        "name": "Kids",
        "count": 420
      },
      {
        "name": "Mystery",
        "count": 416
      },
      {
        "name": "Magic",
        "count": 410
      },
      {
        "name": "Ecchi",
        "count": 373
      },
      {
        "name": "Historical",
        "count": 314
      },
      {
        "name": "Super Power",
        "count": 242
      },
      {
        "name": "Music",
        "count": 233
      },
      {
        "name": "Sports",
        "count": 222
      },
      {
        "name": "Horror",
        "count": 204
      },
      {
        "name": "Military",
        "count": 202
      },
      {
        "name": "Space",
        "count": 184
      },
      {
        "name": "Parody",
        "count": 183
      },
      {
        "name": "Family",
        "count": 178
      },
      {
        "name": "Harem",
        "count": 168
      },
      {
        "name": "Martial Arts",
        "count": 153
      },
      {
        "name": "Psychological",
        "count": 137
      },
      {
        "name": "Demons",
        "count": 136
      },
      {
        "name": "Crime",
        "count": 122
      },
      {
        "name": "Game",
        "count": 113
      },
      {
        "name": "Police",
        "count": 90
      },
      {
        "name": "Friendship",
        "count": 88
      },
      {
        "name": "Anime Influenced",
        "count": 74
      },
      {
        "name": "Mahou Shoujo",
        "count": 67
      },
      {
        "name": "Vampire",
        "count": 59
      },
      {
        "name": "Samurai",
        "count": 59
      },
      {
        "name": "Thriller",
        "count": 58
      },
      {
        "name": "Shounen Ai",
        "count": 46
      },
      {
        "name": "Shoujo Ai",
        "count": 41
      },
      {
        "name": "Short",
        "count": 34
      },
      {
        "name": "Cars",
        "count": 33
      },
      {
        "name": "Sport",
        "count": 32
      },
      {
        "name": "War & Politics",
        "count": 30
      },
      {
        "name": "Dementia",
        "count": 28
      },
      {
        "name": "Yaoi",
        "count": 20
      },
      {
        "name": "Racing",
        "count": 18
      },
      {
        "name": "Food",
        "count": 17
      },
      {
        "name": "History",
        "count": 15
      },
      {
        "name": "Zombies",
        "count": 13
      },
      {
        "name": "Workplace",
        "count": 11
      },
      {
        "name": "Gore",
        "count": 9
      },
      {
        "name": "Gender Bender",
        "count": 8
      },
      {
        "name": "Medical",
        "count": 8
      },
      {
        "name": "Political",
        "count": 7
      },
      {
        "name": "Yuri",
        "count": 7
      },
      {
        "name": "Doujinshi",
        "count": 7
      },
      {
        "name": "Documentary",
        "count": 5
      },
      {
        "name": "Isekai",
        "count": 2
      },
      {
        "name": "Tragedy",
        "count": 2
      },
      {
        "name": "Soap",
        "count": 2
      },
      {
        "name": "Mature",
        "count": 1
      },
      {
        "name": "Law",
        "count": 1
      },
      {
        "name": "Mahou Shounen",
        "count": 1
      },
      {
        "name": "Adult",
        "count": 1
      },
      {
        "name": "Cooking",
        "count": 1
      },
      {
        "name": "Musical",
        "count": 1
      },
      {
        "name": "Western",
        "count": 1
      }
    ]
  },
  "seasons": {
    "withCounts": [
      "2026 - Fall (10)",
      "2026 - Summer (2)",
      "2026 - Spring (5)",
      "2026 - Winter (40)",
      "2025 - Fall (45)",
      "2025 - Summer (50)",
      "2025 - Spring (54)",
      "2025 - Winter (42)",
      "2024 - Fall (44)",
      "2024 - Summer (53)",
      "2024 - Spring (61)",
      "2024 - Winter (45)",
      "2023 - Fall (66)",
      "2023 - Summer (48)",
      "2023 - Spring (63)",
      "2023 - Winter (47)",
      "2022 - Fall (53)",
      "2022 - Summer (56)",
      "2022 - Spring (46)",
      "2022 - Winter (52)",
      "2021 - Fall (53)",
      "2021 - Summer (51)",
      "2021 - Spring (61)",
      "2021 - Winter (58)",
      "2020 - Fall (56)",
      "2020 - Summer (39)",
      "2020 - Spring (53)",
      "2020 - Winter (46)",
      "2019 - Fall (53)",
      "2019 - Summer (46)",
      "2019 - Spring (47)",
      "2019 - Winter (41)",
      "2018 - Fall (57)",
      "2018 - Summer (55)",
      "2018 - Spring (58)",
      "2018 - Winter (56)",
      "2017 - Fall (54)",
      "2017 - Summer (56)",
      "2017 - Spring (54)",
      "2017 - Winter (41)",
      "2016 - Fall (61)",
      "2016 - Summer (57)",
      "2016 - Spring (62)",
      "2016 - Winter (41)",
      "2015 - Fall (61)",
      "2015 - Summer (45)",
      "2015 - Spring (40)",
      "2015 - Winter (31)",
      "2014 - Fall (53)",
      "2014 - Summer (52)",
      "2014 - Spring (53)",
      "2014 - Winter (56)",
      "2013 - Fall (46)",
      "2013 - Summer (44)",
      "2013 - Spring (36)",
      "2013 - Winter (38)",
      "2012 - Fall (48)",
      "2012 - Summer (42)",
      "2012 - Spring (45)",
      "2012 - Winter (46)",
      "2011 - Fall (32)",
      "2011 - Summer (31)",
      "2011 - Spring (36)",
      "2011 - Winter (31)",
      "2010 - Fall (41)",
      "2010 - Summer (30)",
      "2010 - Spring (30)",
      "2010 - Winter (32)",
      "2009 - Fall (36)",
      "2009 - Summer (21)",
      "2009 - Spring (43)",
      "2009 - Winter (28)",
      "2008 - Fall (36)",
      "2008 - Summer (29)",
      "2008 - Spring (41)",
      "2008 - Winter (30)",
      "2007 - Fall (40)",
      "2007 - Summer (23)",
      "2007 - Spring (51)",
      "2007 - Winter (34)",
      "2006 - Fall (45)",
      "2006 - Summer (39)",
      "2006 - Spring (54)",
      "2006 - Winter (31)",
      "2005 - Fall (41)",
      "2005 - Summer (27)",
      "2005 - Spring (39)",
      "2005 - Winter (26)",
      "2004 - Fall (39)",
      "2004 - Summer (20)",
      "2004 - Spring (39)",
      "2004 - Winter (28)",
      "2003 - Fall (38)",
      "2003 - Summer (19)",
      "2003 - Spring (42)",
      "2003 - Winter (21)",
      "2002 - Fall (30)",
      "2002 - Summer (22)",
      "2002 - Spring (26)",
      "2002 - Winter (29)",
      "2001 - Fall (31)",
      "2001 - Summer (16)",
      "2001 - Spring (35)",
      "2001 - Winter (19)",
      "2000 - Fall (22)",
      "2000 - Summer (11)",
      "2000 - Spring (16)",
      "2000 - Winter (21)",
      "1999 - Fall (26)",
      "1999 - Summer (24)",
      "1999 - Spring (23)",
      "1999 - Winter (18)",
      "1998 - Fall (29)",
      "1998 - Summer (9)",
      "1998 - Spring (32)",
      "1998 - Winter (14)",
      "1997 - Fall (14)",
      "1997 - Summer (12)",
      "1997 - Spring (22)",
      "1997 - Winter (13)",
      "1996 - Fall (19)",
      "1996 - Summer (13)",
      "1996 - Spring (17)",
      "1996 - Winter (21)",
      "1995 - Fall (19)",
      "1995 - Summer (8)",
      "1995 - Spring (27)",
      "1995 - Winter (13)",
      "1994 - Fall (18)",
      "1994 - Summer (18)",
      "1994 - Spring (21)",
      "1994 - Winter (12)",
      "1993 - Fall (17)",
      "1993 - Summer (17)",
      "1993 - Spring (20)",
      "1993 - Winter (18)",
      "1992 - Fall (24)",
      "1992 - Summer (25)",
      "1992 - Spring (11)",
      "1992 - Winter (18)",
      "1991 - Fall (18)",
      "1991 - Summer (22)",
      "1991 - Spring (21)",
      "1991 - Winter (20)",
      "1990 - Fall (14)",
      "1990 - Summer (17)",
      "1990 - Spring (13)",
      "1990 - Winter (24)",
      "1989 - Fall (30)",
      "1989 - Summer (15)",
      "1989 - Spring (17)",
      "1989 - Winter (16)",
      "1988 - Fall (20)",
      "1988 - Summer (10)",
      "1988 - Spring (17)",
      "1988 - Winter (9)",
      "1987 - Fall (21)",
      "1987 - Summer (12)",
      "1987 - Spring (12)",
      "1987 - Winter (19)",
      "1986 - Fall (11)",
      "1986 - Summer (15)",
      "1986 - Spring (10)",
      "1986 - Winter (17)",
      "1985 - Fall (16)",
      "1985 - Summer (6)",
      "1985 - Spring (7)",
      "1985 - Winter (11)",
      "1984 - Fall (7)",
      "1984 - Summer (8)",
      "1984 - Spring (7)",
      "1984 - Winter (9)",
      "1983 - Fall (12)",
      "1983 - Summer (6)",
      "1983 - Spring (12)",
      "1983 - Winter (7)",
      "1982 - Fall (7)",
      "1982 - Summer (3)",
      "1982 - Spring (10)",
      "1982 - Winter (4)",
      "1981 - Fall (11)",
      "1981 - Summer (4)",
      "1981 - Spring (6)",
      "1981 - Winter (8)",
      "1980 - Fall (5)",
      "1980 - Summer (6)",
      "1980 - Spring (7)",
      "1980 - Winter (7)",
      "1979 - Fall (6)",
      "1979 - Summer (7)",
      "1979 - Spring (5)",
      "1979 - Winter (7)",
      "1978 - Fall (3)",
      "1978 - Summer (5)",
      "1978 - Spring (6)",
      "1978 - Winter (3)",
      "1977 - Fall (7)",
      "1977 - Summer (3)",
      "1977 - Spring (5)",
      "1977 - Winter (5)",
      "1976 - Fall (4)",
      "1976 - Summer (3)",
      "1976 - Spring (4)",
      "1976 - Winter (3)",
      "1975 - Fall (7)",
      "1975 - Summer (1)",
      "1975 - Spring (6)",
      "1975 - Winter (2)",
      "1974 - Fall (4)",
      "1974 - Summer (1)",
      "1974 - Spring (6)",
      "1974 - Winter (3)",
      "1973 - Fall (6)",
      "1973 - Spring (1)",
      "1973 - Winter (4)",
      "1972 - Fall (4)",
      "1972 - Summer (1)",
      "1972 - Spring (3)",
      "1972 - Winter (2)",
      "1971 - Fall (4)",
      "1971 - Summer (2)",
      "1971 - Winter (3)",
      "1970 - Fall (3)",
      "1970 - Spring (4)",
      "1970 - Winter (1)",
      "1969 - Fall (7)",
      "1969 - Summer (1)",
      "1969 - Spring (2)",
      "1969 - Winter (2)",
      "1968 - Fall (3)",
      "1968 - Summer (1)",
      "1968 - Spring (4)",
      "1968 - Winter (3)",
      "1967 - Fall (2)",
      "1967 - Summer (1)",
      "1967 - Spring (4)",
      "1966 - Fall (1)",
      "1966 - Summer (1)",
      "1966 - Spring (3)",
      "1966 - Winter (1)",
      "1965 - Fall (1)",
      "1965 - Spring (2)",
      "1965 - Winter (1)",
      "1964 - Winter (2)",
      "1963 - Fall (3)",
      "1963 - Winter (1)",
      "1961 - Spring (1)",
      "1960 - Winter (1)"
    ],
    "list": [
      {
        "name": "2026 - Winter",
        "count": 40
      },
      {
        "name": "2026 - Summer",
        "count": 2
      },
      {
        "name": "2026 - Spring",
        "count": 5
      },
      {
        "name": "2026 - Fall",
        "count": 10
      },
      {
        "name": "2025 - Winter",
        "count": 42
      },
      {
        "name": "2025 - Summer",
        "count": 50
      },
      {
        "name": "2025 - Spring",
        "count": 54
      },
      {
        "name": "2025 - Fall",
        "count": 45
      },
      {
        "name": "2024 - Winter",
        "count": 45
      },
      {
        "name": "2024 - Summer",
        "count": 53
      },
      {
        "name": "2024 - Spring",
        "count": 61
      },
      {
        "name": "2024 - Fall",
        "count": 44
      },
      {
        "name": "2023 - Winter",
        "count": 47
      },
      {
        "name": "2023 - Summer",
        "count": 48
      },
      {
        "name": "2023 - Spring",
        "count": 63
      },
      {
        "name": "2023 - Fall",
        "count": 66
      },
      {
        "name": "2022 - Winter",
        "count": 52
      },
      {
        "name": "2022 - Summer",
        "count": 56
      },
      {
        "name": "2022 - Spring",
        "count": 46
      },
      {
        "name": "2022 - Fall",
        "count": 53
      },
      {
        "name": "2021 - Winter",
        "count": 58
      },
      {
        "name": "2021 - Summer",
        "count": 51
      },
      {
        "name": "2021 - Spring",
        "count": 61
      },
      {
        "name": "2021 - Fall",
        "count": 53
      },
      {
        "name": "2020 - Winter",
        "count": 46
      },
      {
        "name": "2020 - Summer",
        "count": 39
      },
      {
        "name": "2020 - Spring",
        "count": 53
      },
      {
        "name": "2020 - Fall",
        "count": 56
      },
      {
        "name": "2019 - Winter",
        "count": 41
      },
      {
        "name": "2019 - Summer",
        "count": 46
      },
      {
        "name": "2019 - Spring",
        "count": 47
      },
      {
        "name": "2019 - Fall",
        "count": 53
      },
      {
        "name": "2018 - Winter",
        "count": 56
      },
      {
        "name": "2018 - Summer",
        "count": 55
      },
      {
        "name": "2018 - Spring",
        "count": 58
      },
      {
        "name": "2018 - Fall",
        "count": 57
      },
      {
        "name": "2017 - Winter",
        "count": 41
      },
      {
        "name": "2017 - Summer",
        "count": 56
      },
      {
        "name": "2017 - Spring",
        "count": 54
      },
      {
        "name": "2017 - Fall",
        "count": 54
      },
      {
        "name": "2016 - Winter",
        "count": 41
      },
      {
        "name": "2016 - Summer",
        "count": 57
      },
      {
        "name": "2016 - Spring",
        "count": 62
      },
      {
        "name": "2016 - Fall",
        "count": 61
      },
      {
        "name": "2015 - Winter",
        "count": 31
      },
      {
        "name": "2015 - Summer",
        "count": 45
      },
      {
        "name": "2015 - Spring",
        "count": 40
      },
      {
        "name": "2015 - Fall",
        "count": 61
      },
      {
        "name": "2014 - Winter",
        "count": 56
      },
      {
        "name": "2014 - Summer",
        "count": 52
      },
      {
        "name": "2014 - Spring",
        "count": 53
      },
      {
        "name": "2014 - Fall",
        "count": 53
      },
      {
        "name": "2013 - Winter",
        "count": 38
      },
      {
        "name": "2013 - Summer",
        "count": 44
      },
      {
        "name": "2013 - Spring",
        "count": 36
      },
      {
        "name": "2013 - Fall",
        "count": 46
      },
      {
        "name": "2012 - Winter",
        "count": 46
      },
      {
        "name": "2012 - Summer",
        "count": 42
      },
      {
        "name": "2012 - Spring",
        "count": 45
      },
      {
        "name": "2012 - Fall",
        "count": 48
      },
      {
        "name": "2011 - Winter",
        "count": 31
      },
      {
        "name": "2011 - Summer",
        "count": 31
      },
      {
        "name": "2011 - Spring",
        "count": 36
      },
      {
        "name": "2011 - Fall",
        "count": 32
      },
      {
        "name": "2010 - Winter",
        "count": 32
      },
      {
        "name": "2010 - Summer",
        "count": 30
      },
      {
        "name": "2010 - Spring",
        "count": 30
      },
      {
        "name": "2010 - Fall",
        "count": 41
      },
      {
        "name": "2009 - Winter",
        "count": 28
      },
      {
        "name": "2009 - Summer",
        "count": 21
      },
      {
        "name": "2009 - Spring",
        "count": 43
      },
      {
        "name": "2009 - Fall",
        "count": 36
      },
      {
        "name": "2008 - Winter",
        "count": 30
      },
      {
        "name": "2008 - Summer",
        "count": 29
      },
      {
        "name": "2008 - Spring",
        "count": 41
      },
      {
        "name": "2008 - Fall",
        "count": 36
      },
      {
        "name": "2007 - Winter",
        "count": 34
      },
      {
        "name": "2007 - Summer",
        "count": 23
      },
      {
        "name": "2007 - Spring",
        "count": 51
      },
      {
        "name": "2007 - Fall",
        "count": 40
      },
      {
        "name": "2006 - Winter",
        "count": 31
      },
      {
        "name": "2006 - Summer",
        "count": 39
      },
      {
        "name": "2006 - Spring",
        "count": 54
      },
      {
        "name": "2006 - Fall",
        "count": 45
      },
      {
        "name": "2005 - Winter",
        "count": 26
      },
      {
        "name": "2005 - Summer",
        "count": 27
      },
      {
        "name": "2005 - Spring",
        "count": 39
      },
      {
        "name": "2005 - Fall",
        "count": 41
      },
      {
        "name": "2004 - Winter",
        "count": 28
      },
      {
        "name": "2004 - Summer",
        "count": 20
      },
      {
        "name": "2004 - Spring",
        "count": 39
      },
      {
        "name": "2004 - Fall",
        "count": 39
      },
      {
        "name": "2003 - Winter",
        "count": 21
      },
      {
        "name": "2003 - Summer",
        "count": 19
      },
      {
        "name": "2003 - Spring",
        "count": 42
      },
      {
        "name": "2003 - Fall",
        "count": 38
      },
      {
        "name": "2002 - Winter",
        "count": 29
      },
      {
        "name": "2002 - Summer",
        "count": 22
      },
      {
        "name": "2002 - Spring",
        "count": 26
      },
      {
        "name": "2002 - Fall",
        "count": 30
      },
      {
        "name": "2001 - Winter",
        "count": 19
      },
      {
        "name": "2001 - Summer",
        "count": 16
      },
      {
        "name": "2001 - Spring",
        "count": 35
      },
      {
        "name": "2001 - Fall",
        "count": 31
      },
      {
        "name": "2000 - Winter",
        "count": 21
      },
      {
        "name": "2000 - Summer",
        "count": 11
      },
      {
        "name": "2000 - Spring",
        "count": 16
      },
      {
        "name": "2000 - Fall",
        "count": 22
      },
      {
        "name": "1999 - Winter",
        "count": 18
      },
      {
        "name": "1999 - Summer",
        "count": 24
      },
      {
        "name": "1999 - Spring",
        "count": 23
      },
      {
        "name": "1999 - Fall",
        "count": 26
      },
      {
        "name": "1998 - Winter",
        "count": 14
      },
      {
        "name": "1998 - Summer",
        "count": 9
      },
      {
        "name": "1998 - Spring",
        "count": 32
      },
      {
        "name": "1998 - Fall",
        "count": 29
      },
      {
        "name": "1997 - Winter",
        "count": 13
      },
      {
        "name": "1997 - Summer",
        "count": 12
      },
      {
        "name": "1997 - Spring",
        "count": 22
      },
      {
        "name": "1997 - Fall",
        "count": 14
      },
      {
        "name": "1996 - Winter",
        "count": 21
      },
      {
        "name": "1996 - Summer",
        "count": 13
      },
      {
        "name": "1996 - Spring",
        "count": 17
      },
      {
        "name": "1996 - Fall",
        "count": 19
      },
      {
        "name": "1995 - Winter",
        "count": 13
      },
      {
        "name": "1995 - Summer",
        "count": 8
      },
      {
        "name": "1995 - Spring",
        "count": 27
      },
      {
        "name": "1995 - Fall",
        "count": 19
      },
      {
        "name": "1994 - Winter",
        "count": 12
      },
      {
        "name": "1994 - Summer",
        "count": 18
      },
      {
        "name": "1994 - Spring",
        "count": 21
      },
      {
        "name": "1994 - Fall",
        "count": 18
      },
      {
        "name": "1993 - Winter",
        "count": 18
      },
      {
        "name": "1993 - Summer",
        "count": 17
      },
      {
        "name": "1993 - Spring",
        "count": 20
      },
      {
        "name": "1993 - Fall",
        "count": 17
      },
      {
        "name": "1992 - Winter",
        "count": 18
      },
      {
        "name": "1992 - Summer",
        "count": 25
      },
      {
        "name": "1992 - Spring",
        "count": 11
      },
      {
        "name": "1992 - Fall",
        "count": 24
      },
      {
        "name": "1991 - Winter",
        "count": 20
      },
      {
        "name": "1991 - Summer",
        "count": 22
      },
      {
        "name": "1991 - Spring",
        "count": 21
      },
      {
        "name": "1991 - Fall",
        "count": 18
      },
      {
        "name": "1990 - Winter",
        "count": 24
      },
      {
        "name": "1990 - Summer",
        "count": 17
      },
      {
        "name": "1990 - Spring",
        "count": 13
      },
      {
        "name": "1990 - Fall",
        "count": 14
      },
      {
        "name": "1989 - Winter",
        "count": 16
      },
      {
        "name": "1989 - Summer",
        "count": 15
      },
      {
        "name": "1989 - Spring",
        "count": 17
      },
      {
        "name": "1989 - Fall",
        "count": 30
      },
      {
        "name": "1988 - Winter",
        "count": 9
      },
      {
        "name": "1988 - Summer",
        "count": 10
      },
      {
        "name": "1988 - Spring",
        "count": 17
      },
      {
        "name": "1988 - Fall",
        "count": 20
      },
      {
        "name": "1987 - Winter",
        "count": 19
      },
      {
        "name": "1987 - Summer",
        "count": 12
      },
      {
        "name": "1987 - Spring",
        "count": 12
      },
      {
        "name": "1987 - Fall",
        "count": 21
      },
      {
        "name": "1986 - Winter",
        "count": 17
      },
      {
        "name": "1986 - Summer",
        "count": 15
      },
      {
        "name": "1986 - Spring",
        "count": 10
      },
      {
        "name": "1986 - Fall",
        "count": 11
      },
      {
        "name": "1985 - Winter",
        "count": 11
      },
      {
        "name": "1985 - Summer",
        "count": 6
      },
      {
        "name": "1985 - Spring",
        "count": 7
      },
      {
        "name": "1985 - Fall",
        "count": 16
      },
      {
        "name": "1984 - Winter",
        "count": 9
      },
      {
        "name": "1984 - Summer",
        "count": 8
      },
      {
        "name": "1984 - Spring",
        "count": 7
      },
      {
        "name": "1984 - Fall",
        "count": 7
      },
      {
        "name": "1983 - Winter",
        "count": 7
      },
      {
        "name": "1983 - Summer",
        "count": 6
      },
      {
        "name": "1983 - Spring",
        "count": 12
      },
      {
        "name": "1983 - Fall",
        "count": 12
      },
      {
        "name": "1982 - Winter",
        "count": 4
      },
      {
        "name": "1982 - Summer",
        "count": 3
      },
      {
        "name": "1982 - Spring",
        "count": 10
      },
      {
        "name": "1982 - Fall",
        "count": 7
      },
      {
        "name": "1981 - Winter",
        "count": 8
      },
      {
        "name": "1981 - Summer",
        "count": 4
      },
      {
        "name": "1981 - Spring",
        "count": 6
      },
      {
        "name": "1981 - Fall",
        "count": 11
      },
      {
        "name": "1980 - Winter",
        "count": 7
      },
      {
        "name": "1980 - Summer",
        "count": 6
      },
      {
        "name": "1980 - Spring",
        "count": 7
      },
      {
        "name": "1980 - Fall",
        "count": 5
      },
      {
        "name": "1979 - Winter",
        "count": 7
      },
      {
        "name": "1979 - Summer",
        "count": 7
      },
      {
        "name": "1979 - Spring",
        "count": 5
      },
      {
        "name": "1979 - Fall",
        "count": 6
      },
      {
        "name": "1978 - Winter",
        "count": 3
      },
      {
        "name": "1978 - Summer",
        "count": 5
      },
      {
        "name": "1978 - Spring",
        "count": 6
      },
      {
        "name": "1978 - Fall",
        "count": 3
      },
      {
        "name": "1977 - Winter",
        "count": 5
      },
      {
        "name": "1977 - Summer",
        "count": 3
      },
      {
        "name": "1977 - Spring",
        "count": 5
      },
      {
        "name": "1977 - Fall",
        "count": 7
      },
      {
        "name": "1976 - Winter",
        "count": 3
      },
      {
        "name": "1976 - Summer",
        "count": 3
      },
      {
        "name": "1976 - Spring",
        "count": 4
      },
      {
        "name": "1976 - Fall",
        "count": 4
      },
      {
        "name": "1975 - Winter",
        "count": 2
      },
      {
        "name": "1975 - Summer",
        "count": 1
      },
      {
        "name": "1975 - Spring",
        "count": 6
      },
      {
        "name": "1975 - Fall",
        "count": 7
      },
      {
        "name": "1974 - Winter",
        "count": 3
      },
      {
        "name": "1974 - Summer",
        "count": 1
      },
      {
        "name": "1974 - Spring",
        "count": 6
      },
      {
        "name": "1974 - Fall",
        "count": 4
      },
      {
        "name": "1973 - Winter",
        "count": 4
      },
      {
        "name": "1973 - Spring",
        "count": 1
      },
      {
        "name": "1973 - Fall",
        "count": 6
      },
      {
        "name": "1972 - Winter",
        "count": 2
      },
      {
        "name": "1972 - Summer",
        "count": 1
      },
      {
        "name": "1972 - Spring",
        "count": 3
      },
      {
        "name": "1972 - Fall",
        "count": 4
      },
      {
        "name": "1971 - Winter",
        "count": 3
      },
      {
        "name": "1971 - Summer",
        "count": 2
      },
      {
        "name": "1971 - Fall",
        "count": 4
      },
      {
        "name": "1970 - Winter",
        "count": 1
      },
      {
        "name": "1970 - Spring",
        "count": 4
      },
      {
        "name": "1970 - Fall",
        "count": 3
      },
      {
        "name": "1969 - Winter",
        "count": 2
      },
      {
        "name": "1969 - Summer",
        "count": 1
      },
      {
        "name": "1969 - Spring",
        "count": 2
      },
      {
        "name": "1969 - Fall",
        "count": 7
      },
      {
        "name": "1968 - Winter",
        "count": 3
      },
      {
        "name": "1968 - Summer",
        "count": 1
      },
      {
        "name": "1968 - Spring",
        "count": 4
      },
      {
        "name": "1968 - Fall",
        "count": 3
      },
      {
        "name": "1967 - Summer",
        "count": 1
      },
      {
        "name": "1967 - Spring",
        "count": 4
      },
      {
        "name": "1967 - Fall",
        "count": 2
      },
      {
        "name": "1966 - Winter",
        "count": 1
      },
      {
        "name": "1966 - Summer",
        "count": 1
      },
      {
        "name": "1966 - Spring",
        "count": 3
      },
      {
        "name": "1966 - Fall",
        "count": 1
      },
      {
        "name": "1965 - Winter",
        "count": 1
      },
      {
        "name": "1965 - Spring",
        "count": 2
      },
      {
        "name": "1965 - Fall",
        "count": 1
      },
      {
        "name": "1964 - Winter",
        "count": 2
      },
      {
        "name": "1963 - Winter",
        "count": 1
      },
      {
        "name": "1963 - Fall",
        "count": 3
      },
      {
        "name": "1961 - Spring",
        "count": 1
      },
      {
        "name": "1960 - Winter",
        "count": 1
      }
    ]
  },
  "weekdays": {
    "withCounts": [
      "Monday (6)",
      "Tuesday (7)",
      "Wednesday (5)",
      "Thursday (7)",
      "Friday (14)",
      "Saturday (9)",
      "Sunday (19)"
    ],
    "list": [
      {
        "name": "Sunday",
        "count": 19
      },
      {
        "name": "Saturday",
        "count": 9
      },
      {
        "name": "Friday",
        "count": 14
      },
      {
        "name": "Monday",
        "count": 6
      },
      {
        "name": "Thursday",
        "count": 7
      },
      {
        "name": "Tuesday",
        "count": 7
      },
      {
        "name": "Wednesday",
        "count": 5
      }
    ]
  },
  "years": [
    {
      "name": "2026",
      "count": 57
    },
    {
      "name": "2025",
      "count": 191
    },
    {
      "name": "2024",
      "count": 203
    },
    {
      "name": "2023",
      "count": 224
    },
    {
      "name": "2022",
      "count": 207
    },
    {
      "name": "2021",
      "count": 223
    },
    {
      "name": "2020",
      "count": 194
    },
    {
      "name": "2019",
      "count": 187
    },
    {
      "name": "2018",
      "count": 226
    },
    {
      "name": "2017",
      "count": 205
    },
    {
      "name": "2016",
      "count": 221
    },
    {
      "name": "2015",
      "count": 177
    },
    {
      "name": "2014",
      "count": 214
    },
    {
      "name": "2013",
      "count": 164
    },
    {
      "name": "2012",
      "count": 181
    },
    {
      "name": "2011",
      "count": 130
    },
    {
      "name": "2010",
      "count": 133
    },
    {
      "name": "2009",
      "count": 128
    },
    {
      "name": "2008",
      "count": 136
    },
    {
      "name": "2007",
      "count": 148
    },
    {
      "name": "2006",
      "count": 169
    },
    {
      "name": "2005",
      "count": 133
    },
    {
      "name": "2004",
      "count": 126
    },
    {
      "name": "2003",
      "count": 120
    },
    {
      "name": "2002",
      "count": 107
    },
    {
      "name": "2001",
      "count": 101
    },
    {
      "name": "2000",
      "count": 70
    },
    {
      "name": "1999",
      "count": 91
    },
    {
      "name": "1998",
      "count": 84
    },
    {
      "name": "1997",
      "count": 61
    },
    {
      "name": "1996",
      "count": 70
    },
    {
      "name": "1995",
      "count": 67
    },
    {
      "name": "1994",
      "count": 69
    },
    {
      "name": "1993",
      "count": 72
    },
    {
      "name": "1992",
      "count": 78
    },
    {
      "name": "1991",
      "count": 81
    },
    {
      "name": "1990",
      "count": 68
    },
    {
      "name": "1989",
      "count": 78
    },
    {
      "name": "1988",
      "count": 56
    },
    {
      "name": "1987",
      "count": 64
    },
    {
      "name": "1986",
      "count": 53
    },
    {
      "name": "1985",
      "count": 40
    },
    {
      "name": "1984",
      "count": 31
    },
    {
      "name": "1983",
      "count": 37
    },
    {
      "name": "1982",
      "count": 24
    },
    {
      "name": "1981",
      "count": 29
    },
    {
      "name": "1980",
      "count": 25
    },
    {
      "name": "1979",
      "count": 25
    },
    {
      "name": "1978",
      "count": 17
    },
    {
      "name": "1977",
      "count": 20
    },
    {
      "name": "1976",
      "count": 14
    },
    {
      "name": "1975",
      "count": 16
    },
    {
      "name": "1974",
      "count": 14
    },
    {
      "name": "1973",
      "count": 11
    },
    {
      "name": "1972",
      "count": 10
    },
    {
      "name": "1971",
      "count": 9
    },
    {
      "name": "1970",
      "count": 8
    },
    {
      "name": "1969",
      "count": 12
    },
    {
      "name": "1968",
      "count": 11
    },
    {
      "name": "1967",
      "count": 7
    },
    {
      "name": "1966",
      "count": 6
    },
    {
      "name": "1965",
      "count": 4
    },
    {
      "name": "1964",
      "count": 2
    },
    {
      "name": "1963",
      "count": 4
    },
    {
      "name": "1961",
      "count": 1
    },
    {
      "name": "1960",
      "count": 1
    }
  ],
  "statuses": [
    {
      "name": "FINISHED",
      "count": 5623
    },
    {
      "name": "ONGOING",
      "count": 102
    },
    {
      "name": "tba",
      "count": 34
    },
    {
      "name": "unreleased",
      "count": 17
    },
    {
      "name": "UPCOMING",
      "count": 3
    }
  ],
  "movieSpecialFilters": {
    "upcoming": 22,
    "newReleases": 28
  },
  "movieGenres": {
    "withCounts": [
      "Animation (1523)",
      "Action (740)",
      "Adventure (727)",
      "Fantasy (567)",
      "Drama (559)",
      "Comedy (542)",
      "Sci-Fi (352)",
      "Kids (204)",
      "Romance (195)",
      "Family (189)",
      "Supernatural (131)",
      "Science Fiction (130)",
      "Mecha (129)",
      "Historical (127)",
      "Mystery (111)",
      "Military (97)",
      "Slice of Life (91)",
      "Super Power (81)",
      "Magic (81)",
      "Space (76)",
      "Music (75)",
      "School (73)",
      "Horror (72)",
      "Sports (68)",
      "Psychological (50)",
      "Friendship (47)",
      "Thriller (45)",
      "Crime (41)",
      "Police (40)",
      "Martial Arts (35)",
      "History (33)",
      "Demons (27)",
      "Dementia (25)",
      "Anime Influenced (25)",
      "Ecchi (23)",
      "Mahou Shoujo (22)",
      "War (21)",
      "Short (21)",
      "Sport (19)",
      "Samurai (18)",
      "Parody (13)",
      "Game (12)",
      "Vampire (10)",
      "Racing (9)",
      "Biography (9)",
      "Cars (8)",
      "Harem (8)",
      "TV Movie (8)",
      "Gore (5)",
      "Zombies (5)",
      "Shounen Ai (3)",
      "Political (3)",
      "Gender Bender (2)",
      "Medical (2)",
      "Musical (2)",
      "Youth (1)",
      "Food (1)",
      "Documentary (1)"
    ],
    "list": [
      {
        "name": "Animation",
        "count": 1523
      },
      {
        "name": "Action",
        "count": 740
      },
      {
        "name": "Adventure",
        "count": 727
      },
      {
        "name": "Fantasy",
        "count": 567
      },
      {
        "name": "Drama",
        "count": 559
      },
      {
        "name": "Comedy",
        "count": 542
      },
      {
        "name": "Sci-Fi",
        "count": 352
      },
      {
        "name": "Kids",
        "count": 204
      },
      {
        "name": "Romance",
        "count": 195
      },
      {
        "name": "Family",
        "count": 189
      },
      {
        "name": "Supernatural",
        "count": 131
      },
      {
        "name": "Science Fiction",
        "count": 130
      },
      {
        "name": "Mecha",
        "count": 129
      },
      {
        "name": "Historical",
        "count": 127
      },
      {
        "name": "Mystery",
        "count": 111
      },
      {
        "name": "Military",
        "count": 97
      },
      {
        "name": "Slice of Life",
        "count": 91
      },
      {
        "name": "Super Power",
        "count": 81
      },
      {
        "name": "Magic",
        "count": 81
      },
      {
        "name": "Space",
        "count": 76
      },
      {
        "name": "Music",
        "count": 75
      },
      {
        "name": "School",
        "count": 73
      },
      {
        "name": "Horror",
        "count": 72
      },
      {
        "name": "Sports",
        "count": 68
      },
      {
        "name": "Psychological",
        "count": 50
      },
      {
        "name": "Friendship",
        "count": 47
      },
      {
        "name": "Thriller",
        "count": 45
      },
      {
        "name": "Crime",
        "count": 41
      },
      {
        "name": "Police",
        "count": 40
      },
      {
        "name": "Martial Arts",
        "count": 35
      },
      {
        "name": "History",
        "count": 33
      },
      {
        "name": "Demons",
        "count": 27
      },
      {
        "name": "Dementia",
        "count": 25
      },
      {
        "name": "Anime Influenced",
        "count": 25
      },
      {
        "name": "Ecchi",
        "count": 23
      },
      {
        "name": "Mahou Shoujo",
        "count": 22
      },
      {
        "name": "War",
        "count": 21
      },
      {
        "name": "Short",
        "count": 21
      },
      {
        "name": "Sport",
        "count": 19
      },
      {
        "name": "Samurai",
        "count": 18
      },
      {
        "name": "Parody",
        "count": 13
      },
      {
        "name": "Game",
        "count": 12
      },
      {
        "name": "Vampire",
        "count": 10
      },
      {
        "name": "Racing",
        "count": 9
      },
      {
        "name": "Biography",
        "count": 9
      },
      {
        "name": "Cars",
        "count": 8
      },
      {
        "name": "Harem",
        "count": 8
      },
      {
        "name": "TV Movie",
        "count": 8
      },
      {
        "name": "Gore",
        "count": 5
      },
      {
        "name": "Zombies",
        "count": 5
      },
      {
        "name": "Shounen Ai",
        "count": 3
      },
      {
        "name": "Political",
        "count": 3
      },
      {
        "name": "Gender Bender",
        "count": 2
      },
      {
        "name": "Medical",
        "count": 2
      },
      {
        "name": "Musical",
        "count": 2
      },
      {
        "name": "Youth",
        "count": 1
      },
      {
        "name": "Food",
        "count": 1
      },
      {
        "name": "Documentary",
        "count": 1
      }
    ]
  }
}